{
    "identifier": {
        "identifier": "MIDAS-ISG:galapagos-input-format-v2.0",
        "identifierSource": "MIDAS-ISG"
    },
    "name": "Galapagos CSV",
    "type": {
        "value": "disease transmission model output",
        "valueIRI": ""
    },
    "description": "This specification describes a tabular format in which output from a disease transmission model is represented.",
    "licenses": [
        {
            "name": "CC BY 3.0 US"
        }
    ],
    "version": "2",
    "extraProperties": [
        {
            "category": "human-readable specification of data format",
            "categoryIRI": "",
            "values": [
                {
                    "value": "https://github.com/midas-isg/data-format-repository/wiki/Galapagos-Output-Format",
                    "valueIRI": ""
                }
            ]
        },
        {
            "category": "validator",
            "categoryIRI": "",
            "values": [
                {
                    "value": "",
                    "valueIRI": ""
                }
            ]
        }
    ]
}